{
  "date": "2015-08-11",
  "title": "Summer Music For Your Collection",
  "description": "Where can you hear the music Michael Franti, Greg Allman, Ashley Monroe and Tom Waits all in one place?  Maybe your smart phone…but most definitely right here on Cyprus Avenue… Gregg Allman",
  "tracks": [
    {
      "artist": "Michael Franti",
      "song": "Once A Day"
    },
    {
      "artist": "Kasey Chambers",
      "song": "Is God Real"
    },
    {
      "artist": "Greg Allman",
      "song": "These Days"
    },
    {
      "artist": "Ashley Monroe",
      "song": "Winning Streaks"
    },
    {
      "artist": "Leon Bridges",
      "song": "Twistin’ & Groovin’"
    },
    {
      "artist": "Greg Allman",
      "song": "Love Like Kerosene"
    },
    {
      "artist": "Chris Stapleton",
      "song": "Might As Well Got Stoned"
    },
    {
      "artist": "Steeldrivers",
      "song": "Six Feet Away"
    },
    {
      "artist": "Ashley Monroe",
      "song": "Dixie"
    },
    {
      "artist": "Greg Allman",
      "song": "Midnight Rider"
    },
    {
      "artist": "Nathaniel Rateliff & The Night Sweats",
      "song": "S.O.B."
    },
    {
      "artist": "Tom Waits",
      "song": "Standing On The Corner"
    }
  ],
  "source_url": "https://www.kcur.org/tags/cyprus-avenue",
  "archived_date": "2025-12-30"
}