{
  "date": "2017-03-09",
  "title": "The Jefferson Airplane",
  "description": "The music of the Jefferson Airplane has been described as, \"...a hallucinatory distillation of folk-blues vocals, garage-rock guitar and crisp pop songwriting.\"  Would you agree?  If your memory of this great band is a bit foggy, check out this week's edition of Cyprus Avenue.",
  "tracks": [
    {
      "artist": "Jefferson Airplane",
      "song": "Bringing Me Down"
    },
    {
      "artist": "The Jefferson Airplane",
      "song": "Chauffer Blues"
    },
    {
      "artist": "The Jefferson Airplane",
      "song": "“Somebody To Love"
    },
    {
      "artist": "The Jefferson Airplane",
      "song": "Today"
    },
    {
      "artist": "The Jefferson Airplane",
      "song": "White Rabbit"
    },
    {
      "artist": "The Jefferson Airplane",
      "song": "She Has Funny Cars"
    },
    {
      "artist": "The Jefferson Airplane",
      "song": "The Ballad Of You & Me Pooneil"
    },
    {
      "artist": "The Jefferson Airplane",
      "song": "Wooden Ships"
    },
    {
      "artist": "The Jefferson Airplane",
      "song": "Jefferson Airplane"
    },
    {
      "artist": "The Jefferson Airplane",
      "song": "Volunteers"
    },
    {
      "artist": "The Jefferson Airplane",
      "song": "We Can Be Together"
    }
  ],
  "source_url": "https://www.kcur.org/tags/cyprus-avenue",
  "archived_date": "2025-12-31"
}